true_storage/__init__.py
true_storage/__true_cache__/__main__.cache
true_storage/base.py
true_storage/database/__init__.py
true_storage/database/filesystem.py
true_storage/database/redis_store.py
true_storage/database/sqlite.py
true_storage/demos/__init__.py
true_storage/demos/all/01_basic.py
true_storage/demos/all/__init__.py
true_storage/demos/all/demo_cold_storage/metadata.json
true_storage/demos/database/01_basic_sqlite.py
true_storage/demos/database/02_filesystem_store.py
true_storage/demos/database/README.md
true_storage/demos/env/.env
true_storage/demos/env/01_basic_env.py
true_storage/demos/env/02_mode_specific.py
true_storage/demos/env/03_snapshots.py
true_storage/demos/env/04_advanced.py
true_storage/demos/env/__init__.py
true_storage/demos/env/README.md
true_storage/demos/session/01_basic_session.py
true_storage/demos/session/02_expiration.py
true_storage/demos/session/03_locking.py
true_storage/demos/session/04_persistence.py
true_storage/demos/session/05_advanced.py
true_storage/demos/session/README.md
true_storage/demos/session/session_data/sessions.json
true_storage/demos/storage/01_hot_storage.py
true_storage/demos/storage/02_cold_storage.py
true_storage/demos/storage/03_mixed_storage.py
true_storage/demos/storage/README.md
true_storage/env.py
true_storage/exceptions.py
true_storage/session.py
true_storage/storage/__init__.py
true_storage/storage/base.py
true_storage/storage/cold.py
true_storage/storage/hot.py
true_storage/storage/mixed.py
true_storage-0.1.0.dist-info/LICENSE.txt
true_storage-0.1.0.dist-info/METADATA
true_storage-0.1.0.dist-info/WHEEL
true_storage-0.1.0.dist-info/RECORD
