Metadata-Version: 2.1
Name: true-storage
Version: 0.1.0
Summary: A boilerplate utility package
Home-page: https://github.com/alaamer12/true-storage
License: MIT
Author: alaamer12
Author-email: ahmedmuhmmed239@gmail.com
Requires-Python: >=3.11,<4.0
Classifier: Development Status :: 4 - Beta
Classifier: Intended Audience :: Developers
Classifier: License :: OSI Approved :: MIT License
Classifier: Programming Language :: Python :: 3
Classifier: Programming Language :: Python :: 3.11
Classifier: Programming Language :: Python :: 3.12
Classifier: Programming Language :: Python :: 3.13
Classifier: Topic :: Software Development :: Libraries :: Python Modules
Provides-Extra: orjson
Provides-Extra: pydantic
Requires-Dist: python-dotenv (>=1.0.1,<2.0.0)
Requires-Dist: redis (>=5.2.0,<6.0.0)
Project-URL: Documentation, https://true-storage.readthedocs.io/en/latest/
Project-URL: Repository, https://github.com/alaamer12/true-storage
